humemai_research/__init__.py
humemai_research/memory.py
humemai_research/utils.py
humemai_research/janusgraph/__init__.py
humemai_research/janusgraph/humemai.py
humemai_research/janusgraph/agent/__init__.py
humemai_research/janusgraph/agent/prompt_agent.py
humemai_research/janusgraph/agent/prompt_chatbot.py
humemai_research/janusgraph/utils/__init__.py
humemai_research/janusgraph/utils/docker.py
humemai_research/prompt/__init__.py
humemai_research/prompt/prompt.py
humemai_research/prompt/templates/__init__.py
humemai_research/prompt/templates/graph2text_with_properties.py
humemai_research/prompt/templates/graph2text_without_properties.py
humemai_research/prompt/templates/text2graph_with_properties.py
humemai_research/prompt/templates/text2graph_without_properties.py
humemai_research/rdflib/__init__.py
humemai_research/rdflib/humemai.py
humemai_research-2.5.6.post2.dist-info/licenses/LICENSE
humemai_research-2.5.6.post2.dist-info/METADATA
humemai_research-2.5.6.post2.dist-info/WHEEL
humemai_research-2.5.6.post2.dist-info/top_level.txt
humemai_research-2.5.6.post2.dist-info/RECORD
