Metadata-Version: 2.4
Name: humemai-research
Version: 2.5.6.post2
Summary: A Machine With Human-Like Memory
Home-page: https://github.com/humemai/humemai-research-research
Author: Taewoon Kim
Author-email: info@humem.ai
Project-URL: Bug Tracker, https://github.com/humemai/humemai-research-research/issues
Classifier: Programming Language :: Python :: 3
Classifier: License :: OSI Approved :: MIT License
Classifier: Operating System :: OS Independent
Requires-Python: >=3.10
License-File: LICENSE
Requires-Dist: rdflib
Requires-Dist: docker
Requires-Dist: sparqlwrapper
Requires-Dist: nest_asyncio
Requires-Dist: gremlinpython
Requires-Dist: transformers
Requires-Dist: torch
Provides-Extra: dev
Requires-Dist: black; extra == "dev"
Requires-Dist: black[jupyter]; extra == "dev"
Requires-Dist: flake8; extra == "dev"
Requires-Dist: mdformat; extra == "dev"
Requires-Dist: isort; extra == "dev"
Requires-Dist: pytest; extra == "dev"
Requires-Dist: ipython; extra == "dev"
Requires-Dist: ipykernel; extra == "dev"
Requires-Dist: tqdm; extra == "dev"
Requires-Dist: huggingface_hub[cli]; extra == "dev"
Requires-Dist: accelerate; extra == "dev"
Dynamic: license-file
